propeller/__init__.py
propeller/types.py
propeller/util.py
propeller/data/__init__.py
propeller/data/example_pb2.py
propeller/data/feature_column.py
propeller/data/feature_pb2.py
propeller/data/functional.py
propeller/paddle/__init__.py
propeller/paddle/collection.py
propeller/paddle/summary.py
propeller/paddle/data/__init__.py
propeller/paddle/data/example_pb2.py
propeller/paddle/data/feature_column.py
propeller/paddle/data/feature_pb2.py
propeller/paddle/data/functional.py
propeller/paddle/train/__init__.py
propeller/paddle/train/distribution.py
propeller/paddle/train/exporter.py
propeller/paddle/train/hooks.py
propeller/paddle/train/metrics.py
propeller/paddle/train/monitored_executor.py
propeller/paddle/train/trainer.py
propeller/service/__init__.py
propeller/service/client.py
propeller/service/interface_pb2.py
propeller/service/server.py
propeller/service/utils.py
propeller/tools/__init__.py
propeller/tools/ckpt_inspector.py
propeller/tools/start_server.py
propeller/train/__init__.py
propeller/train/model.py
paddle_propeller-0.5.1.dev1.dist-info/LICENSE
paddle_propeller-0.5.1.dev1.dist-info/METADATA
paddle_propeller-0.5.1.dev1.dist-info/WHEEL
paddle_propeller-0.5.1.dev1.dist-info/top_level.txt
paddle_propeller-0.5.1.dev1.dist-info/RECORD
