Metadata-Version: 2.1
Name: paddle-propeller
Version: 0.5.1.dev1
Summary: high level paddle-paddle API
Home-page: https://github.com/PaddlePaddle/ERNIE
Author: Chen Xuyi
Author-email: chen_xuyi@outlook.com
License: Apache 2.0
Platform: UNKNOWN
Requires-Python: >= 2.6.*
Requires-Dist: paddlepaddle
